vending_machine/vending_mealy.v
module vending_mealy(
    input  wire        clk,
    input  wire        rst,       // sync active-high
    input  wire [1:0]  coin,      // 01=5, 10=10, 00=idle
    output wire        dispense,  // 1-cycle pulse
    output wire        chg5       // 1-cycle pulse when returning 5
);

    // Define states for totals 0, 5, 10, 15
    parameter S_0  = 2'b00;
    parameter S_5  = 2'b01;
    parameter S_10 = 2'b10;
    parameter S_15 = 2'b11;

    // Define coin values for readability
    parameter COIN_IDLE = 2'b00;
    parameter COIN_5    = 2'b01;
    parameter COIN_10   = 2'b10;

    // State registers
    reg [1:0] current_state, next_state;

    // Mealy outputs must be registered to be set in the combinational block
    reg dispense_reg, chg5_reg;
    assign dispense = dispense_reg;
    assign chg5 = chg5_reg;

    // 1. Sequential Logic: State Register
    // This block handles state transitions on the clock edge and synchronous reset.
    always @(posedge clk) begin
        if (rst) begin
            current_state <= S_0;
        end else begin
            current_state <= next_state;
        end
    end

    // 2. Combinational Logic: Next State and Mealy Outputs
    // This block determines the next state and outputs based on the
    // current state AND the current inputs.
    always @(*) begin
        // Default assignments to avoid latches and define default behavior
        next_state = current_state;
        dispense_reg = 1'b0;
        chg5_reg = 1'b0;

        case (current_state)
            S_0: begin
                if (coin == COIN_5)       next_state = S_5;
                else if (coin == COIN_10) next_state = S_10;
            end
            S_5: begin
                if (coin == COIN_5)       next_state = S_10;
                else if (coin == COIN_10) next_state = S_15;
            end
            S_10: begin
                if (coin == COIN_5)       next_state = S_15;
                else if (coin == COIN_10) begin
                    next_state = S_0;
                    dispense_reg = 1'b1; // Output depends on input
                end
            end
            S_15: begin
                if (coin == COIN_5) begin
                    next_state = S_0;
                    dispense_reg = 1'b1; // Output depends on input
                end else if (coin == COIN_10) begin
                    next_state = S_0;
                    dispense_reg = 1'b1; // Output depends on input
                    chg5_reg = 1'b1;     // and this one too
                end
            end
            default: begin
                next_state = S_0;
            end
        endcase
    end

endmodule

vending_machine/tb_vending_mealy.v
module tb_vending_mealy;

    // Testbench signals
    reg clk;
    reg rst;
    reg [1:0] coin;
    wire dispense;
    wire chg5;

    // Constants for testability
    parameter COIN_IDLE = 2'b00;
    parameter COIN_5    = 2'b01;
    parameter COIN_10   = 2'b10;

    // Instantiate the Device Under Test (DUT)
    vending_mealy dut (
        .clk(clk),
        .rst(rst),
        .coin(coin),
        .dispense(dispense),
        .chg5(chg5)
    );

    // Clock Generator
    parameter CLK_PERIOD = 10;
    initial begin
        clk = 0;
        forever #(CLK_PERIOD/2) clk = ~clk;
    end

    // Simulation Stimulus
    initial begin
        // For waveform viewing
        $dumpfile("waveform.vcd");
        $dumpvars(0, tb_vending_mealy);

        // 1. Apply Reset
        rst = 1;
        coin = COIN_IDLE;
        @(posedge clk);
        @(posedge clk);
        rst = 0;
        @(posedge clk);

        // 2. Scenario 1: Simple Vend (10 + 10 = 20)
        $display("Test 1: Inserting 10 + 10");
        coin <= COIN_10; @(posedge clk); // Total = 10
        coin <= COIN_10; @(posedge clk); // Total = 20. dispense should pulse now
        coin <= COIN_IDLE; @(posedge clk); // Back to idle.

        #20;

        // 3. Scenario 2: Vend with Change (5 + 10 + 10 = 25)
        $display("Test 2: Inserting 5 + 10 + 10");
        coin <= COIN_5; @(posedge clk);  // Total = 5
        coin <= COIN_10; @(posedge clk); // Total = 15
        coin <= COIN_10; @(posedge clk); // Total = 25. dispense and chg5 should pulse now
        coin <= COIN_IDLE; @(posedge clk);

        #20;

        // 4. Scenario 3: Another simple vend (5+5+5+5)
        $display("Test 3: Inserting 5 + 5 + 5 + 5");
        coin <= COIN_5; @(posedge clk); // Total = 5
        coin <= COIN_5; @(posedge clk); // Total = 10
        coin <= COIN_5; @(posedge clk); // Total = 15
        coin <= COIN_5; @(posedge clk); // Total = 20. dispense should pulse now
        coin <= COIN_IDLE; @(posedge clk);

        // End simulation
        #50;
        $display("Testbench finished.");
        $finish;
    end

endmodule

vending_machine/waveform.vcd
$date
	Tue Aug 19 02:05:34 2025
$end
$version
	Icarus Verilog
$end
$timescale
	1s
$end
$scope module tb_vending_mealy $end
$var wire 1 ! dispense $end
$var wire 1 " chg5 $end
$var parameter 32 # CLK_PERIOD $end
$var parameter 2 $ COIN_10 $end
$var parameter 2 % COIN_5 $end
$var parameter 2 & COIN_IDLE $end
$var reg 1 ' clk $end
$var reg 2 ( coin [1:0] $end
$var reg 1 ) rst $end
$scope module dut $end
$var wire 1 " chg5 $end
$var wire 1 ' clk $end
$var wire 2 * coin [1:0] $end
$var wire 1 ! dispense $end
$var wire 1 ) rst $end
$var parameter 2 + COIN_10 $end
$var parameter 2 , COIN_5 $end
$var parameter 2 - COIN_IDLE $end
$var parameter 2 . S_0 $end
$var parameter 2 / S_10 $end
$var parameter 2 0 S_15 $end
$var parameter 2 1 S_5 $end
$var reg 1 2 chg5_reg $end
$var reg 2 3 current_state [1:0] $end
$var reg 1 4 dispense_reg $end
$var reg 2 5 next_state [1:0] $end
$upscope $end
$upscope $end
$enddefinitions $end
$comment Show the parameter values. $end
$dumpall
b1 1
b11 0
b10 /
b0 .
b0 -
b1 ,
b10 +
b0 &
b1 %
b10 $
b1010 #
$end
#0
$dumpvars
b0 5
04
bx 3
02
b0 *
1)
b0 (
0'
0"
0!
$end
#5
b0 3
1'
#10
0'
#15
0)
1'
#20
0'
#25
b10 5
b10 (
b10 *
1'
#30
0'
#35
1!
14
b0 5
b10 3
1'
#40
0'
#45
0!
04
b0 3
b0 (
b0 *
1'
#50
0'
#55
1'
#60
0'
#65
1'
#70
0'
#75
b10 5
b10 (
b10 *
1'
#80
0'
#85
1!
14
b0 5
b10 3
1'
#90
0'
#95
0!
04
b0 3
b0 (
b0 *
1'
#100
0'
#105
1'
#110
0'
#115
1'
#120
0'
#125
b1 5
b1 (
b1 *
1'
#130
0'
#135
b10 5
b1 3
1'
#140
0'
#145
b11 5
b10 3
1'
#150
0'
#155
b0 (
b0 *
b11 3
1'
