LAB2/seq_detect_mealy.v
module seq_detect_mealy(
    input  wire clk,
    input  wire rst,
    input  wire din,
    output wire y    // The output wire
);

// State encoding
localparam S0 = 2'b00, S1 = 2'b01, S2 = 2'b10, S3 = 2'b11;

// Internal state register
reg [1:0] current_state, next_state;

// Internal register for the combinational output
reg y_reg;

// Continuous assignment to drive the output wire from the internal register
assign y = y_reg;

// Sequential logic for state transitions
always @(posedge clk) begin
    if (rst) begin
        current_state <= S0;
    end else begin
        current_state <= next_state;
    end
end

// Combinational logic for next state and Mealy output
always @(*) begin
    next_state = current_state; // Default to stay in the same state
    y_reg = 1'b0; // Default output is 0

    case(current_state)
        S0: begin
            if (din) begin
                next_state = S1;
            end
        end
        S1: begin
            if (din) begin
                next_state = S2;
            end else begin
                next_state = S0;
            end
        end
        S2: begin
            if (din) begin
                next_state = S2;
            end else begin
                next_state = S3;
            end
        end
        S3: begin
            if (din) begin
                next_state = S2;
                y_reg = 1'b1; // Assign to the internal register
            end else begin
                next_state = S0;
            end
        end
        default: begin
            next_state = S0;
        end
    endcase
end

endmodule

LAB2/tb_seq_detect_mealy.v
// Testbench for the seq_detect_mealy module
module tb_seq_detect_mealy;

// Signals for the testbench
reg clk, rst, din;
wire y;

// Instantiate the DUT
seq_detect_mealy dut(.clk(clk), .rst(rst), .din(din), .y(y));

// Clock generation
initial begin
    clk = 0;
    forever #5 clk = ~clk;
end

// Stimulus generation
initial begin
    // Synchronous reset
    rst = 1;
    din = 0;
    #10;
    rst = 0;

    // Test sequence: 1101101101
    // Expected pulses: at the end of the 1st, 2nd, and 3rd "1101" patterns.
    // The pulses will appear at simulation times 40, 80, and 100 ns.
    din = 1; #10;
    din = 1; #10;
    din = 0; #10;
    din = 1; #10; // First pattern "1101" is detected.
    din = 1; #10;
    din = 0; #10;
    din = 1; #10;
    din = 1; #10; // Second pattern "1101" is detected.
    din = 0; #10;
    din = 1; #10; // Third pattern "1101" is detected.

    // End simulation
    #50;
    $finish;
end

// Waveform and log file dumping
initial begin
    $dumpfile("dump.vcd");
    $dumpvars(0, tb_seq_detect_mealy);
    $monitor("Time=%0t, rst=%b, din=%b, y=%b", $time, rst, din, y);
end

endmodule

LAB2/dump.vcd
$date
	Tue Aug 19 01:45:34 2025
$end
$version
	Icarus Verilog
$end
$timescale
	1s
$end
$scope module tb_seq_detect_mealy $end
$var wire 1 ! y $end
$var reg 1 " clk $end
$var reg 1 # din $end
$var reg 1 $ rst $end
$scope module dut $end
$var wire 1 " clk $end
$var wire 1 # din $end
$var wire 1 $ rst $end
$var wire 1 ! y $end
$var parameter 2 % S0 $end
$var parameter 2 & S1 $end
$var parameter 2 ' S2 $end
$var parameter 2 ( S3 $end
$var reg 2 ) current_state [1:0] $end
$var reg 2 * next_state [1:0] $end
$var reg 1 + y_reg $end
$upscope $end
$upscope $end
$enddefinitions $end
$comment Show the parameter values. $end
$dumpall
b11 (
b10 '
b1 &
b0 %
$end
#0
$dumpvars
0+
b0 *
bx )
1$
0#
0"
0!
$end
#5
b0 )
1"
#10
b1 *
0"
1#
0$
#15
b10 *
b1 )
1"
#20
0"
#25
b10 )
1"
#30
b11 *
0"
0#
#35
b0 *
b11 )
1"
#40
1!
1+
b10 *
0"
1#
#45
0!
0+
b10 )
1"
#50
0"
#55
1"
#60
b11 *
0"
0#
#65
b0 *
b11 )
1"
#70
1!
1+
b10 *
0"
1#
#75
0!
0+
b10 )
1"
#80
0"
#85
1"
#90
b11 *
0"
0#
#95
b0 *
b11 )
1"
#100
1!
1+
b10 *
0"
1#
#105
0!
0+
b10 )
1"
