traffic_light/traffic_light.v
module traffic_light(
    input  wire clk,
    input  wire rst,         // sync active-high
    input  wire tick,        // 1-cycle per-second pulse
    output wire ns_g, ns_y, ns_r,
    output wire ew_g, ew_y, ew_r
);

    // 1. Define States using parameters for readability
    parameter NS_GREEN  = 2'b00;
    parameter NS_YELLOW = 2'b01;
    parameter EW_GREEN  = 2'b10;
    parameter EW_YELLOW = 2'b11;

    // Define timing constants
    parameter GREEN_TICKS = 5;
    parameter YELLOW_TICKS = 2;

    // 2. Internal Registers
    reg [1:0] current_state, next_state;
    reg [2:0] tick_counter; // Counter needs to hold up to 5, so 3 bits is enough

    // 3. Sequential Logic: State Register and Per-Phase Counter
    always @(posedge clk) begin
        if (rst) begin
            current_state <= NS_GREEN;
            tick_counter  <= 0;
        end else begin
            // On a state change, reset the counter. Otherwise, update the state.
            if (current_state != next_state) begin
                tick_counter <= 0;
            end else if (tick) begin // Increment counter only on a tick
                tick_counter <= tick_counter + 1;
            end
            current_state <= next_state;
        end
    end

    // 4. Combinational Logic: Next State Determination
    always @(*) begin
        next_state = current_state; // Default: stay in the same state
        case (current_state)
            NS_GREEN: begin
                if (tick && (tick_counter == GREEN_TICKS - 1)) begin
                    next_state = NS_YELLOW;
                end
            end
            NS_YELLOW: begin
                if (tick && (tick_counter == YELLOW_TICKS - 1)) begin
                    next_state = EW_GREEN;
                end
            end
            EW_GREEN: begin
                if (tick && (tick_counter == GREEN_TICKS - 1)) begin
                    next_state = EW_YELLOW;
                end
            end
            EW_YELLOW: begin
                if (tick && (tick_counter == YELLOW_TICKS - 1)) begin
                    next_state = NS_GREEN;
                end
            end
            default: next_state = NS_GREEN;
        endcase
    end

    // 5. Combinational Logic: Output Determination (Moore FSM)
    // Outputs are assigned using intermediate registers to be set by the case statement.
    reg ns_g_reg, ns_y_reg, ns_r_reg;
    reg ew_g_reg, ew_y_reg, ew_r_reg;

    assign ns_g = ns_g_reg;
    assign ns_y = ns_y_reg;
    assign ns_r = ns_r_reg;
    assign ew_g = ew_g_reg;
    assign ew_y = ew_y_reg;
    assign ew_r = ew_r_reg;

    always @(*) begin
        // Default all lights to off to avoid latches
        {ns_g_reg, ns_y_reg, ns_r_reg} = 3'b000;
        {ew_g_reg, ew_y_reg, ew_r_reg} = 3'b000;

        case (current_state)
            NS_GREEN: begin
                ns_g_reg = 1'b1; // NS is Green
                ew_r_reg = 1'b1; // EW is Red
            end
            NS_YELLOW: begin
                ns_y_reg = 1'b1; // NS is Yellow
                ew_r_reg = 1'b1; // EW is Red
            end
            EW_GREEN: begin
                ew_g_reg = 1'b1; // EW is Green
                ns_r_reg = 1'b1; // NS is Red
            end
            EW_YELLOW: begin
                ew_y_reg = 1'b1; // EW is Yellow
                ns_r_reg = 1'b1; // NS is Red
            end
            default: begin // Default to a safe state (all red)
                ns_r_reg = 1'b1;
                ew_r_reg = 1'b1;
            end
        endcase
    end

endmodule

traffic_light/tb_traffic_light.v
module tb_traffic_light;

    // 1. Testbench Signals
    reg clk;
    reg rst;
    reg tick;

    wire ns_g, ns_y, ns_r;
    wire ew_g, ew_y, ew_r;

    // 2. Instantiate the Device Under Test (DUT)
    traffic_light dut (
        .clk(clk),
        .rst(rst),
        .tick(tick),
        .ns_g(ns_g), .ns_y(ns_y), .ns_r(ns_r),
        .ew_g(ew_g), .ew_y(ew_y), .ew_r(ew_r)
    );

    // 3. Clock Generator (e.g., 100MHz clock -> 10ns period)
    parameter CLK_PERIOD = 10;
    initial begin
        clk = 0;
        forever #(CLK_PERIOD/2) clk = ~clk;
    end

    // 4. Tick Generator (produces a 1-cycle pulse every 10 clock cycles)
    // This simulates the 1Hz tick in an efficient way.
    integer tick_gen_counter = 0;
    always @(posedge clk) begin
        if (rst) begin
            tick <= 0;
            tick_gen_counter <= 0;
        end else begin
            if (tick_gen_counter == 9) begin
                tick <= 1;
                tick_gen_counter <= 0;
            end else begin
                tick <= 0;
                tick_gen_counter <= tick_gen_counter + 1;
            end
        end
    end

    // 5. Simulation Control and Stimulus
    initial begin
        // For waveform viewing
        $dumpfile("waveform.vcd");
        $dumpvars(0, tb_traffic_light);

        // Apply reset
        rst = 1;
        tick = 0;
        @(posedge clk);
        @(posedge clk);
        rst = 0;

        // Run simulation for a few full cycles and then stop
        #2000; // Run for 2000 time units
        $finish;
    end

endmodule

traffic_light/waveform.vcd
$date
	Tue Aug 19 01:53:46 2025
$end
$version
	Icarus Verilog
$end
$timescale
	1s
$end
$scope module tb_traffic_light $end
$var wire 1 ! ns_y $end
$var wire 1 " ns_r $end
$var wire 1 # ns_g $end
$var wire 1 $ ew_y $end
$var wire 1 % ew_r $end
$var wire 1 & ew_g $end
$var parameter 32 ' CLK_PERIOD $end
$var reg 1 ( clk $end
$var reg 1 ) rst $end
$var reg 1 * tick $end
$var integer 32 + tick_gen_counter [31:0] $end
$scope module dut $end
$var wire 1 ( clk $end
$var wire 1 & ew_g $end
$var wire 1 % ew_r $end
$var wire 1 $ ew_y $end
$var wire 1 # ns_g $end
$var wire 1 " ns_r $end
$var wire 1 ! ns_y $end
$var wire 1 ) rst $end
$var wire 1 * tick $end
$var parameter 2 , EW_GREEN $end
$var parameter 2 - EW_YELLOW $end
$var parameter 32 . GREEN_TICKS $end
$var parameter 2 / NS_GREEN $end
$var parameter 2 0 NS_YELLOW $end
$var parameter 32 1 YELLOW_TICKS $end
$var reg 2 2 current_state [1:0] $end
$var reg 1 3 ew_g_reg $end
$var reg 1 4 ew_r_reg $end
$var reg 1 5 ew_y_reg $end
$var reg 2 6 next_state [1:0] $end
$var reg 1 7 ns_g_reg $end
$var reg 1 8 ns_r_reg $end
$var reg 1 9 ns_y_reg $end
$var reg 3 : tick_counter [2:0] $end
$upscope $end
$upscope $end
$enddefinitions $end
$comment Show the parameter values. $end
$dumpall
b10 1
b1 0
b0 /
b101 .
b11 -
b10 ,
b1010 '
$end
#0
$dumpvars
bx :
x9
x8
x7
b0 6
x5
x4
x3
bx 2
b0 +
0*
1)
0(
x&
x%
x$
x#
x"
x!
$end
#5
0&
03
0$
05
1%
14
1#
17
0!
09
0"
08
b0 :
b0 2
1(
#10
0(
#15
0)
1(
#20
0(
#25
b1 +
1(
#30
0(
#35
b10 +
1(
#40
0(
#45
b11 +
1(
#50
0(
#55
b100 +
1(
#60
0(
#65
b101 +
1(
#70
0(
#75
b110 +
1(
#80
0(
#85
b111 +
1(
#90
0(
#95
b1000 +
1(
#100
0(
#105
b1001 +
1(
#110
0(
#115
b0 +
1*
1(
#120
0(
#125
b1 :
b1 +
0*
1(
#130
0(
#135
b10 +
1(
#140
0(
#145
b11 +
1(
#150
0(
#155
b100 +
1(
#160
0(
#165
b101 +
1(
#170
0(
#175
b110 +
1(
#180
0(
#185
b111 +
1(
#190
0(
#195
b1000 +
1(
#200
0(
#205
b1001 +
1(
#210
0(
#215
b0 +
1*
1(
#220
0(
#225
b10 :
b1 +
0*
1(
#230
0(
#235
b10 +
1(
#240
0(
#245
b11 +
1(
#250
0(
#255
b100 +
1(
#260
0(
#265
b101 +
1(
#270
0(
#275
b110 +
1(
#280
0(
#285
b111 +
1(
#290
0(
#295
b1000 +
1(
#300
0(
#305
b1001 +
1(
#310
0(
#315
b0 +
1*
1(
#320
0(
#325
b11 :
b1 +
0*
1(
#330
0(
#335
b10 +
1(
#340
0(
#345
b11 +
1(
#350
0(
#355
b100 +
1(
#360
0(
#365
b101 +
1(
#370
0(
#375
b110 +
1(
#380
0(
#385
b111 +
1(
#390
0(
#395
b1000 +
1(
#400
0(
#405
b1001 +
1(
#410
0(
#415
b0 +
1*
1(
#420
0(
#425
b100 :
b1 +
0*
1(
#430
0(
#435
b10 +
1(
#440
0(
#445
b11 +
1(
#450
0(
#455
b100 +
1(
#460
0(
#465
b101 +
1(
#470
0(
#475
b110 +
1(
#480
0(
#485
b111 +
1(
#490
0(
#495
b1000 +
1(
#500
0(
#505
b1001 +
1(
#510
0(
#515
b1 6
b0 +
1*
1(
#520
0(
#525
1!
19
1%
14
0#
07
b1 2
b0 :
b1 +
0*
1(
#530
0(
#535
b10 +
1(
#540
0(
#545
b11 +
1(
#550
0(
#555
b100 +
1(
#560
0(
#565
b101 +
1(
#570
0(
#575
b110 +
1(
#580
0(
#585
b111 +
1(
#590
0(
#595
b1000 +
1(
#600
0(
#605
b1001 +
1(
#610
0(
#615
b0 +
1*
1(
#620
0(
#625
b1 :
b1 +
0*
1(
#630
0(
#635
b10 +
1(
#640
0(
#645
b11 +
1(
#650
0(
#655
b100 +
1(
#660
0(
#665
b101 +
1(
#670
0(
#675
b110 +
1(
#680
0(
#685
b111 +
1(
#690
0(
#695
b1000 +
1(
#700
0(
#705
b1001 +
1(
#710
0(
#715
b10 6
b0 +
1*
1(
#720
0(
#725
1"
18
1&
13
0%
04
0!
09
b10 2
b0 :
b1 +
0*
1(
#730
0(
#735
b10 +
1(
#740
0(
#745
b11 +
1(
#750
0(
#755
b100 +
1(
#760
0(
#765
b101 +
1(
#770
0(
#775
b110 +
1(
#780
0(
#785
b111 +
1(
#790
0(
#795
b1000 +
1(
#800
0(
#805
b1001 +
1(
#810
0(
#815
b0 +
1*
1(
#820
0(
#825
b1 :
b1 +
0*
1(
#830
0(
#835
b10 +
1(
#840
0(
#845
b11 +
1(
#850
0(
#855
b100 +
1(
#860
0(
#865
b101 +
1(
#870
0(
#875
b110 +
1(
#880
0(
#885
b111 +
1(
#890
0(
#895
b1000 +
1(
#900
0(
#905
b1001 +
1(
#910
0(
#915
b0 +
1*
1(
#920
0(
#925
b10 :
b1 +
0*
1(
#930
0(
#935
b10 +
1(
#940
0(
#945
b11 +
1(
#950
0(
#955
b100 +
1(
#960
0(
#965
b101 +
1(
#970
0(
#975
b110 +
1(
#980
0(
#985
b111 +
1(
#990
0(
#995
b1000 +
1(
#1000
0(
#1005
b1001 +
1(
#1010
0(
#1015
b0 +
1*
1(
#1020
0(
#1025
b11 :
b1 +
0*
1(
#1030
0(
#1035
b10 +
1(
#1040
0(
#1045
b11 +
1(
#1050
0(
#1055
b100 +
1(
#1060
0(
#1065
b101 +
1(
#1070
0(
#1075
b110 +
1(
#1080
0(
#1085
b111 +
1(
#1090
0(
#1095
b1000 +
1(
#1100
0(
#1105
b1001 +
1(
#1110
0(
#1115
b0 +
1*
1(
#1120
0(
#1125
b100 :
b1 +
0*
1(
#1130
0(
#1135
b10 +
1(
#1140
0(
#1145
b11 +
1(
#1150
0(
#1155
b100 +
1(
#1160
0(
#1165
b101 +
1(
#1170
0(
#1175
b110 +
1(
#1180
0(
#1185
b111 +
1(
#1190
0(
#1195
b1000 +
1(
#1200
0(
#1205
b1001 +
1(
#1210
0(
#1215
b11 6
b0 +
1*
1(
#1220
0(
#1225
1$
15
0&
03
1"
18
b11 2
b0 :
b1 +
0*
1(
#1230
0(
#1235
b10 +
1(
#1240
0(
#1245
b11 +
1(
#1250
0(
#1255
b100 +
1(
#1260
0(
#1265
b101 +
1(
#1270
0(
#1275
b110 +
1(
#1280
0(
#1285
b111 +
1(
#1290
0(
#1295
b1000 +
1(
#1300
0(
#1305
b1001 +
1(
#1310
0(
#1315
b0 +
1*
1(
#1320
0(
#1325
b1 :
b1 +
0*
1(
#1330
0(
#1335
b10 +
1(
#1340
0(
#1345
b11 +
1(
#1350
0(
#1355
b100 +
1(
#1360
0(
#1365
b101 +
1(
#1370
0(
#1375
b110 +
1(
#1380
0(
#1385
b111 +
1(
#1390
0(
#1395
b1000 +
1(
#1400
0(
#1405
b1001 +
1(
#1410
0(
#1415
b0 6
b0 +
1*
1(
#1420
0(
#1425
1%
14
1#
17
0$
05
0"
08
b0 2
b0 :
b1 +
0*
1(
#1430
0(
#1435
b10 +
1(
#1440
0(
#1445
b11 +
1(
#1450
0(
#1455
b100 +
1(
#1460
0(
#1465
b101 +
1(
#1470
0(
#1475
b110 +
1(
#1480
0(
#1485
b111 +
1(
#1490
0(
#1495
b1000 +
1(
#1500
0(
#1505
b1001 +
1(
#1510
0(
#1515
b0 +
1*
1(
#1520
0(
#1525
b1 :
b1 +
0*
1(
#1530
0(
#1535
b10 +
1(
#1540
0(
#1545
b11 +
1(
#1550
0(
#1555
b100 +
1(
#1560
0(
#1565
b101 +
1(
#1570
0(
#1575
b110 +
1(
#1580
0(
#1585
b111 +
1(
#1590
0(
#1595
b1000 +
1(
#1600
0(
#1605
b1001 +
1(
#1610
0(
#1615
b0 +
1*
1(
#1620
0(
#1625
b10 :
b1 +
0*
1(
#1630
0(
#1635
b10 +
1(
#1640
0(
#1645
b11 +
1(
#1650
0(
#1655
b100 +
1(
#1660
0(
#1665
b101 +
1(
#1670
0(
#1675
b110 +
1(
#1680
0(
#1685
b111 +
1(
#1690
0(
#1695
b1000 +
1(
#1700
0(
#1705
b1001 +
1(
#1710
0(
#1715
b0 +
1*
1(
#1720
0(
#1725
b11 :
b1 +
0*
1(
#1730
0(
#1735
b10 +
1(
#1740
0(
#1745
b11 +
1(
#1750
0(
#1755
b100 +
1(
#1760
0(
#1765
b101 +
1(
#1770
0(
#1775
b110 +
1(
#1780
0(
#1785
b111 +
1(
#1790
0(
#1795
b1000 +
1(
#1800
0(
#1805
b1001 +
1(
#1810
0(
#1815
b0 +
1*
1(
#1820
0(
#1825
b100 :
b1 +
0*
1(
#1830
0(
#1835
b10 +
1(
#1840
0(
#1845
b11 +
1(
#1850
0(
#1855
b100 +
1(
#1860
0(
#1865
b101 +
1(
#1870
0(
#1875
b110 +
1(
#1880
0(
#1885
b111 +
1(
#1890
0(
#1895
b1000 +
1(
#1900
0(
#1905
b1001 +
1(
#1910
0(
#1915
b1 6
b0 +
1*
1(
#1920
0(
#1925
1!
19
1%
14
0#
07
b1 2
b0 :
b1 +
0*
1(
#1930
0(
#1935
b10 +
1(
#1940
0(
#1945
b11 +
1(
#1950
0(
#1955
b100 +
1(
#1960
0(
#1965
b101 +
1(
#1970
0(
#1975
b110 +
1(
#1980
0(
#1985
b111 +
1(
#1990
0(
#1995
b1000 +
1(
#2000
0(
#2005
b1001 +
1(
#2010
0(
#2015
b0 +
1*
1(
